pytetris/__main__.py
pytetris/ai.py
pytetris/assets/font/HYXiaoBoHuaYueYuanW.ttf
pytetris/assets/image/background1.png
pytetris/assets/image/background2.png
pytetris/assets/image/background3.png
pytetris/assets/image/background4.png
pytetris/assets/image/background5.png
pytetris/assets/image/background6.png
pytetris/assets/image/blue_lg.png
pytetris/assets/image/blue_lg_pushed.png
pytetris/assets/image/blue_sm.png
pytetris/assets/image/blue_sm_pushed.png
pytetris/assets/image/green.png
pytetris/assets/image/green_pushed.png
pytetris/assets/image/icon.png
pytetris/assets/image/logo.png
pytetris/assets/image/red.png
pytetris/assets/image/red_pushed.png
pytetris/assets/music/bgm.ogg
pytetris/assets/music/biu1.ogg
pytetris/assets/music/biu2.ogg
pytetris/assets/music/clear.ogg
pytetris/assets/music/drop.ogg
pytetris/assets/music/end.ogg
pytetris/assets/music/start.ogg
pytetris/game.py
pytetris/matrix.py
pytetris/store.py
pytetris/tetris.py
pytetris/typing.py
pytetris-1.0.0.dist-info/entry_points.txt
pytetris-1.0.0.dist-info/LICENSE
pytetris-1.0.0.dist-info/WHEEL
pytetris-1.0.0.dist-info/METADATA
pytetris-1.0.0.dist-info/RECORD
