Metadata-Version: 2.1
Name: pytetris
Version: 1.0.0
Summary: tetris game with ai made by pygame
Home-page: https://github.com/yanyongyu/python-tetris
License: MIT
Keywords: pygame,tetris,ai,pierre_dellacherie
Author: yanyongyu
Author-email: https://github.com/yanyongyu
Requires-Python: >=3.6,<4.0
Classifier: Development Status :: 5 - Production/Stable
Classifier: Intended Audience :: End Users/Desktop
Classifier: License :: Free for non-commercial use
Classifier: License :: OSI Approved :: MIT License
Classifier: Programming Language :: Python
Classifier: Programming Language :: Python :: 3
Classifier: Programming Language :: Python :: 3.6
Classifier: Programming Language :: Python :: 3.7
Classifier: Programming Language :: Python :: 3.8
Classifier: Topic :: Games/Entertainment :: Puzzle Games
Requires-Dist: numpy (>=1.18.1,<2.0.0)
Requires-Dist: pygame (>=1.9.6,<2.0.0)
Project-URL: Repository, https://github.com/yanyongyu/python-tetris
